<?xml version="1.0" encoding="utf-8" ?>
<dwsync>
<file name="close.png" server="C:/wamp/www/ProyectoIntranetDimarsaOriginal/servidor/" local="130176307520000000" remote="130176307520000000" Dst="1" />
<file name="loading.gif" server="C:/wamp/www/ProyectoIntranetDimarsaOriginal/servidor/" local="130176307520000000" remote="130176307520000000" Dst="1" />
<file name="next.png" server="C:/wamp/www/ProyectoIntranetDimarsaOriginal/servidor/" local="130176307520000000" remote="130176307520000000" Dst="1" />
<file name="prev.png" server="C:/wamp/www/ProyectoIntranetDimarsaOriginal/servidor/" local="130176307520000000" remote="130176307520000000" Dst="1" />
<file name="close.png" server="C:/wamp/www/movilDW/" local="130176307520000000" remote="130176307520000000" Dst="1" />
<file name="loading.gif" server="C:/wamp/www/movilDW/" local="130176307520000000" remote="130176307520000000" Dst="1" />
<file name="prev.png" server="C:/wamp/www/movilDW/" local="130176307520000000" remote="130176307520000000" Dst="1" />
<file name="next.png" server="C:/wamp/www/movilDW/" local="130176307520000000" remote="130176307520000000" Dst="1" />
<file name="img_1.jpg" server="C:/wamp/www/movilDW/" local="130396346811452319" remote="130396346810000000" Dst="1" />
<file name="img_2.jpg" server="C:/wamp/www/movilDW/" local="130397958334436161" remote="130397958330000000" Dst="1" />
<file name="img_3.jpg" server="C:/wamp/www/movilDW/" local="130396343980700409" remote="130396343980000000" Dst="1" />
<file name="img_4.jpg" server="C:/wamp/www/movilDW/" local="130396342919229696" remote="130396342910000000" Dst="1" />
<file name="img_5.jpg" server="C:/wamp/www/movilDW/" local="130396342713777945" remote="130396342710000000" Dst="1" />
<file name="img_6.jpg" server="C:/wamp/www/movilDW/" local="130396343393266810" remote="130396343390000000" Dst="1" />
<file name="img_7.jpg" server="C:/wamp/www/movilDW/" local="128564061340000000" remote="128564061340000000" Dst="1" />
<file name="logo_1.jpg" server="C:/wamp/www/movilDW/" local="129331851080000000" remote="129331851080000000" Dst="1" />
<file name="logo_2.jpg" server="C:/wamp/www/movilDW/" local="129331851080000000" remote="129331851080000000" Dst="1" />
<file name="logo_3.jpg" server="C:/wamp/www/movilDW/" local="129331851080000000" remote="129331851080000000" Dst="1" />
<file name="logo_4.jpg" server="C:/wamp/www/movilDW/" local="129331851080000000" remote="129331851080000000" Dst="1" />
<file name="logo_5.jpg" server="C:/wamp/www/movilDW/" local="129331851080000000" remote="129331851080000000" Dst="1" />
<file name="logo_6.jpg" server="C:/wamp/www/movilDW/" local="129331851080000000" remote="129331851080000000" Dst="1" />
<file name="logo_7.jpg" server="C:/wamp/www/movilDW/" local="129331851080000000" remote="129331851080000000" Dst="1" />
<file name="logo_cam1.png" server="C:/wamp/www/movilDW/" local="130385054239319195" remote="130385054230000000" Dst="1" />
<file name="logo_cam2.png" server="C:/wamp/www/movilDW/" local="130391962314324235" remote="130391962310000000" Dst="1" />
<file name="logo_cam3.png" server="C:/wamp/www/movilDW/" local="130391963808969724" remote="130391963800000000" Dst="1" />
<file name="logo_cam4.png" server="C:/wamp/www/movilDW/" local="130391962086071179" remote="130391962080000000" Dst="1" />
<file name="logo_camOriginal.jpg" server="C:/wamp/www/movilDW/" local="129332054380000000" remote="129332054380000000" Dst="1" />
</dwsync>